LICENSE
README.md
setup.cfg
setup.py
stacs/ci/__about__.py
stacs/ci/__init__.py
stacs/ci/constants.py
stacs/ci/diff.py
stacs/ci/exceptions.py
stacs/ci/helpers.py
stacs/ci/models.py
stacs/ci/generic/__init__.py
stacs/ci/generic/__main__.py
stacs/ci/generic/fail.py
stacs/ci/github/__init__.py
stacs/ci/github/__main__.py
stacs/ci/github/client.py
stacs/ci/github/constants.py
stacs/ci/github/pr.py
stacs_ci.egg-info/PKG-INFO
stacs_ci.egg-info/SOURCES.txt
stacs_ci.egg-info/dependency_links.txt
stacs_ci.egg-info/requires.txt
stacs_ci.egg-info/top_level.txt