Metadata-Version: 2.1
Name: stacs-ci
Version: 0.1.5
Summary: Static Token And Credential Scanner CI Integrations.
Home-page: https://www.github.com/stacscan/stacs-integration/
License: BSD
Platform: UNKNOWN
Classifier: Programming Language :: Python :: 3.9
Classifier: Natural Language :: English
Requires-Python: >=3.9
Provides-Extra: development
License-File: LICENSE
